modcs_mercupy/__init__.py
modcs_mercupy/mercupy.py
modcs_mercupy-0.0.2.dist-info/METADATA
modcs_mercupy-0.0.2.dist-info/WHEEL
modcs_mercupy-0.0.2.dist-info/licenses/LICENSE
modcs_mercupy-0.0.2.dist-info/RECORD
