Metadata-Version: 2.3
Name: modcs-mercupy
Version: 0.0.2
Summary: A package that abstracts the Mercury's script language in Python.
Project-URL: Homepage, https://gitlab.cin.ufpe.br/mjas/mercupy
Author-email: Marcelo Santana <mjas@cin.ufpe.br>
Maintainer-email: Marcelo Santana <mjas@cin.ufpe.br>, Jônatas Iago <jis@cin.ufpe.br>, Vinícius Almeida <vsa@cin.ufpe.br>
License-File: LICENSE
Classifier: License :: OSI Approved :: BSD License
Classifier: Operating System :: OS Independent
Classifier: Programming Language :: Python :: 3
Requires-Python: >=3.8
